setup.py
ntfs/BinaryParser.py
ntfs/FileMap.py
ntfs/Progress.py
ntfs/SortedCollection.py
ntfs/__init__.py
ntfs/mft/MFT.py
ntfs/mft/__init__.py
python_ntfs.egg-info/PKG-INFO
python_ntfs.egg-info/SOURCES.txt
python_ntfs.egg-info/dependency_links.txt
python_ntfs.egg-info/requires.txt
python_ntfs.egg-info/top_level.txt