Metadata-Version: 1.1
Name: python-ntfs
Version: 0.1
Summary: Open source Python library for NTFS analysis
Home-page: http://www.williballenthin.com/forensics/ntfs
Author: Willi Ballenthin
Author-email: willi.ballenthin@gmail.com
License: Apache License (2.0)
Platform: UNKNOWN
Classifier: Programming Language :: Python
Classifier: Operating System :: OS Independent
Classifier: License :: OSI Approved :: Apache Software License
